pothead/__init__.py
pothead/cgroups.py
pothead/gating.py
pothead/oob_response.py
pothead/resource_balancer.py
pothead/server.py
pothead/subprocess_middleware.py
pothead/test_cgroups.py
pothead/test_resource_balancer.py
pothead/test_subprocess_middleware.py
pothead/test_worker.py
pothead/util.py
pothead/worker.py
pothead/wsgi_typing.py
pothead/subprocess_metrics/__init__.py
pothead/subprocess_metrics/test_metrics.py
POTHEAD-0.10.6.dist-info/LICENSE
POTHEAD-0.10.6.dist-info/METADATA
POTHEAD-0.10.6.dist-info/WHEEL
POTHEAD-0.10.6.dist-info/top_level.txt
POTHEAD-0.10.6.dist-info/RECORD
