Metadata-Version: 2.1
Name: POTHEAD
Version: 0.10.6
Summary: A reverse-http proxy implementation for non-concurrent requests
Home-page: https://gitlab.com/rawler/pothead
Author: Ulrik Mikaelsson
Author-email: ulrik.mikaelsson@gmail.com
Classifier: Programming Language :: Python :: 3
Classifier: License :: OSI Approved :: Apache Software License
Classifier: Operating System :: OS Independent
License-File: LICENSE
Requires-Dist: prometheus-client
Requires-Dist: psutil
Requires-Dist: setproctitle
Requires-Dist: tblib
Requires-Dist: werkzeug >=2.1
Provides-Extra: test
Requires-Dist: aiohttp ; extra == 'test'
Requires-Dist: prometheus-client ; extra == 'test'
Requires-Dist: psutil ; extra == 'test'
Requires-Dist: setproctitle ; extra == 'test'
Requires-Dist: tblib ; extra == 'test'
Requires-Dist: timeout-decorator ; extra == 'test'
Requires-Dist: werkzeug >=2.1 ; extra == 'test'
